tachyon/__init__.py
tachyon/__main__.py
tachyon/__version__.py
tachyon/conf.py
tachyon/config.py
tachyon/database.py
tachyon/dbutils.py
tachyon/directoryfetcher.py
tachyon/filefetcher.py
tachyon/generator.py
tachyon/har.py
tachyon/loaders.py
tachyon/output.py
tachyon/result.py
tachyon/textutils.py
tachyon/data/files.json
tachyon/data/paths.json
tachyon/heuristics/__init__.py
tachyon/heuristics/logbehaviorchange.py
tachyon/heuristics/matchstring.py
tachyon/heuristics/rejectignoredquery.py
tachyon/heuristics/striptag.py
tachyon/plugins/__init__.py
tachyon/plugins/file/__init__.py
tachyon/plugins/host/HostProcessor.py
tachyon/plugins/host/PathGenerator.py
tachyon/plugins/host/Robots.py
tachyon/plugins/host/SitemapXML.py
tachyon/plugins/host/Svn.py
tachyon/plugins/host/__init__.py
tachyon3-3.5.5.dist-info/LICENSE.md
tachyon3-3.5.5.dist-info/METADATA
tachyon3-3.5.5.dist-info/WHEEL
tachyon3-3.5.5.dist-info/entry_points.txt
tachyon3-3.5.5.dist-info/top_level.txt
tachyon3-3.5.5.dist-info/RECORD
