Metadata-Version: 2.1
Name: tachyon3
Version: 3.5.5
Summary: UNKNOWN
Home-page: https://github.com/delvelabs/tachyon
License: UNKNOWN
Platform: UNKNOWN
Requires-Python: >=3.12.0,<4
License-File: LICENSE.md
Requires-Dist: click <9,>=7.1.2
Requires-Dist: easyinject <0.4,>=0.3
Requires-Dist: hammertime-http <0.11,>=0.8
Requires-Dist: simhash ==2.1.2
